kalavai_client/__init__.py
kalavai_client/__main__.py
kalavai_client/api.py
kalavai_client/api_models.py
kalavai_client/assets/__init__.py
kalavai_client/assets/apps.yaml
kalavai_client/assets/default_pool_config.yaml
kalavai_client/assets/docker-compose-gui.yaml
kalavai_client/assets/docker-compose-template.yaml
kalavai_client/assets/model_deployment_values.yaml
kalavai_client/assets/nginx.conf
kalavai_client/assets/pool_config_template.yaml
kalavai_client/assets/user_workspace.yaml
kalavai_client/assets/user_workspace_values.yaml
kalavai_client/auth.py
kalavai_client/cli.py
kalavai_client/cluster.py
kalavai_client/core.py
kalavai_client/env.py
kalavai_client/utils.py
kalavai_client-0.8.13.dist-info/METADATA
kalavai_client-0.8.13.dist-info/WHEEL
kalavai_client-0.8.13.dist-info/entry_points.txt
kalavai_client-0.8.13.dist-info/licenses/LICENSE
kalavai_client-0.8.13.dist-info/RECORD
