Metadata-Version: 2.4
Name: kalavai-client
Version: 0.8.13
Summary: Client app for kalavai platform
License-Expression: Apache-2.0
License-File: LICENSE
Keywords: LLM,platform
Author: Carlos Fernandez Musoles
Author-email: carlos@kalavai.net
Maintainer: Carlos Fernandez Musoles
Maintainer-email: carlos@kalavai.net
Requires-Python: >=3.12
Classifier: Programming Language :: Python :: 3
Classifier: Programming Language :: Python :: 3.12
Classifier: Programming Language :: Python :: 3.13
Classifier: Programming Language :: Python :: 3.14
Provides-Extra: dev
Requires-Dist: Pillow (==10.3.0)
Requires-Dist: arguably (>=1.2.5)
Requires-Dist: build ; extra == "dev"
Requires-Dist: fastapi (==0.115.8)
Requires-Dist: fastapi-mcp (==0.3.0)
Requires-Dist: importlib_resources (==6.5.2)
Requires-Dist: jinja2 (==3.1.4)
Requires-Dist: netifaces (==0.11.0)
Requires-Dist: psutil (==5.9.8)
Requires-Dist: public-ip (==0.12)
Requires-Dist: py2app (==0.28.7) ; extra == "dev"
Requires-Dist: pydantic (==2.10.6)
Requires-Dist: pyinstaller (==6.5.0) ; extra == "dev"
Requires-Dist: pyyaml (==6.0.2)
Requires-Dist: requests (>=2.25)
Requires-Dist: rich (==13.7.1)
Requires-Dist: setuptools (>75.0.0)
Requires-Dist: twine ; extra == "dev"
Requires-Dist: uvicorn (==0.34.0)
Project-URL: Homepage, https://platform.kalavai.net
Project-URL: Website, https://kalavai.net
